covid_fit/__init__.py
covid_fit/fit_functions/__init__.py
covid_fit/fit_functions/funcs.py
covid_fit/fit_utilities/__init__.py
covid_fit/fit_utilities/fit.py
covid_fit/fit_utilities/pull_data.py
covid_fit-0.3.1.dist-info/LICENSE
covid_fit-0.3.1.dist-info/METADATA
covid_fit-0.3.1.dist-info/WHEEL
covid_fit-0.3.1.dist-info/top_level.txt
covid_fit-0.3.1.dist-info/RECORD
