Metadata-Version: 2.1
Name: covid-fit
Version: 0.3.1
Summary: Fit utilities to analyze covid data
Home-page: https://github.com/robomorelli/covid_fit
Author: Roberto Morelli
Author-email: roberto.morelli7@unibo.it
License: UNKNOWN
Platform: UNKNOWN
Requires-Dist: requests
Requires-Dist: pandas
Requires-Dist: scipy
Requires-Dist: numpy
Requires-Dist: matplotlib
Requires-Dist: datetime
